{"version": "1.2", "metadata": {"title": "believer", "beats_in_measure": "4", "BPM": "163", "key": "C", "YouTubeID": "XfuBREMXxts", "mode": "1", "duration": "5.81"}, "tracks": {"melody": [{"scale_degree": "4", "octave": "0", "isRest": false, "event_on": 0.0, "event_off": 1.0, "event_duration": 1.0}, {"scale_degree": "4", "octave": "0", "isRest": false, "event_on": 1.0, "event_off": 2.0, "event_duration": 1.0}, {"scale_degree": "3", "octave": "0", "isRest": false, "event_on": 2.0, "event_off": 3.0, "event_duration": 1.0}, {"scale_degree": "3", "octave": "0", "isRest": false, "event_on": 3.0, "event_off": 4.0, "event_duration": 1.0}, {"scale_degree": "1", "octave": "0", "isRest": false, "event_on": 4.0, "event_off": 4.5, "event_duration": 0.5}, {"scale_degree": "2", "octave": "0", "isRest": false, "event_on": 4.5, "event_off": 5.0, "event_duration": 0.5}, {"scale_degree": "4", "octave": "0", "isRest": false, "event_on": 5.0, "event_off": 5.5, "event_duration": 0.5}, {"scale_degree": "1", "octave": "0", "isRest": false, "event_on": 5.5, "event_off": 6.0, "event_duration": 0.5}, {"scale_degree": "2", "octave": "0", "isRest": false, "event_on": 6.0, "event_off": 6.5, "event_duration": 0.5}, {"scale_degree": "4", "octave": "0", "isRest": false, "event_on": 6.5, "event_off": 7.0, "event_duration": 0.5}, {"scale_degree": "1", "octave": "0", "isRest": false, "event_on": 7.0, "event_off": 7.5, "event_duration": 0.5}, {"scale_degree": "2", "octave": "0", "isRest": false, "event_on": 7.5, "event_off": 8.0, "event_duration": 0.5}, {"scale_degree": "1", "octave": "0", "isRest": false, "event_on": 8.0, "event_off": 8.5, "event_duration": 0.5}, {"scale_degree": "2", "octave": "0", "isRest": false, "event_on": 8.5, "event_off": 9.0, "event_duration": 0.5}, {"scale_degree": "4", "octave": "0", "isRest": false, "event_on": 9.0, "event_off": 9.5, "event_duration": 0.5}, {"scale_degree": "1", "octave": "0", "isRest": false, "event_on": 9.5, "event_off": 10.0, "event_duration": 0.5}, {"scale_degree": "2", "octave": "0", "isRest": false, "event_on": 10.0, "event_off": 10.5, "event_duration": 0.5}, {"scale_degree": "4", "octave": "0", "isRest": false, "event_on": 10.5, "event_off": 11.0, "event_duration": 0.5}, {"scale_degree": "1", "octave": "0", "isRest": false, "event_on": 11.0, "event_off": 12.0, "event_duration": 1.0}], "chord": [{"sd": "5", "fb": "7", "sec": null, "sus": null, "pedal": null, "alternate": null, "borrowed": null, "isRest": false, "event_on": 0.0, "event_off": 2.0, "event_duration": 2.0}, {"sd": "1", "fb": null, "sec": null, "sus": null, "pedal": null, "alternate": null, "borrowed": null, "isRest": false, "event_on": 2.0, "event_off": 4.0, "event_duration": 2.0}, {"sd": "5", "fb": null, "sec": null, "sus": null, "pedal": null, "alternate": null, "borrowed": null, "isRest": false, "event_on": 4.0, "event_off": 5.0, "event_duration": 1.0}, {"sd": "rest", "fb": null, "sec": null, "sus": null, "pedal": null, "alternate": null, "borrowed": null, "isRest": true, "event_on": 5.0, "event_off": 6.0, "event_duration": 1.0}, {"sd": "rest", "fb": null, "sec": null, "sus": null, "pedal": null, "alternate": null, "borrowed": null, "isRest": true, "event_on": 6.0, "event_off": 7.0, "event_duration": 1.0}, {"sd": "rest", "fb": null, "sec": null, "sus": null, "pedal": null, "alternate": null, "borrowed": null, "isRest": true, "event_on": 7.0, "event_off": 8.0, "event_duration": 1.0}, {"sd": "rest", "fb": null, "sec": null, "sus": null, "pedal": null, "alternate": null, "borrowed": null, "isRest": true, "event_on": 8.0, "event_off": 9.0, "event_duration": 1.0}, {"sd": "rest", "fb": null, "sec": null, "sus": null, "pedal": null, "alternate": null, "borrowed": null, "isRest": true, "event_on": 9.0, "event_off": 10.0, "event_duration": 1.0}, {"sd": "rest", "fb": null, "sec": null, "sus": null, "pedal": null, "alternate": null, "borrowed": null, "isRest": true, "event_on": 10.0, "event_off": 11.0, "event_duration": 1.0}, {"sd": "rest", "fb": null, "sec": null, "sus": null, "pedal": null, "alternate": null, "borrowed": null, "isRest": true, "event_on": 11.0, "event_off": 12.0, "event_duration": 1.0}]}, "num_measures": 3.0, "audio_features": {"danceability": 0.526, "energy": 0.775, "key": 0, "loudness": -6.05, "mode": 1, "speechiness": 0.0352, "acousticness": 0.707, "instrumentalness": 2.05e-05, "liveness": 0.217, "valence": 0.962, "tempo": 80.106, "id": "3G7tRC24Uh09Hmp1KZ7LQ2", "duration_ms": 167373, "time_signature": 4}}